genguardx/__init__.py
genguardx/exceptions.py
genguardx/py.typed
genguardx/test_init.py
genguardx/version.txt
genguardx/_internal/__init__.py
genguardx/_internal/annotation_queue.py
genguardx/_internal/attachments.py
genguardx/_internal/data_tables.py
genguardx/_internal/helpers.py
genguardx/_internal/models.py
genguardx/_internal/monitoring.py
genguardx/_internal/pipelines.py
genguardx/_internal/prompts.py
genguardx/_internal/quality_check.py
genguardx/_internal/rags.py
genguardx/_internal/resources.py
genguardx/_internal/settings.py
genguardx/_internal/sync.py
genguardx/_internal/test_data_tables.py
genguardx/_internal/test_resources.py
genguardx/_internal/test_settings.py
genguardx/_internal/mixins/__init__.py
genguardx/_internal/mixins/auditable.py
genguardx/_internal/mixins/searchable.py
genguardx/_internal/mixins/shareable.py
genguardx/_internal/mixins/simulatable.py
genguardx/_internal/mixins/test_auditable.py
genguardx/_internal/mixins/test_simulatable.py
genguardx/_internal/mixins/test_with_fields.py
genguardx/_internal/mixins/test_workflowable.py
genguardx/_internal/mixins/with_fields.py
genguardx/_internal/mixins/with_notes.py
genguardx/_internal/mixins/with_python_code.py
genguardx/_internal/mixins/workflowable.py
genguardx/_internal/reports/__init__.py
genguardx/_internal/reports/templates.py
genguardx/_internal/reports/test_templates.py
genguardx/_internal/util/__init__.py
genguardx/_internal/util/base_api.py
genguardx/_internal/util/constants.py
genguardx/_internal/util/get_annotations.py
genguardx/_internal/util/lang_utils.py
genguardx/_internal/util/networking.py
genguardx/_internal/util/test_base_api.py
genguardx/_internal/util/test_constants.py
genguardx/_internal/util/test_lang_utils.py
genguardx/_internal/util/test_networking.py
genguardx/_internal/util/utils.py
genguardx-2025.10.12.dist-info/METADATA
genguardx-2025.10.12.dist-info/WHEEL
genguardx-2025.10.12.dist-info/top_level.txt
genguardx-2025.10.12.dist-info/RECORD
