Metadata-Version: 2.4
Name: genguardx
Version: 2025.10.12
Project-URL: Homepage, https://ggx.corridorplatforms.com
Project-URL: Documentation, https://ggx-docs.corridorplatforms.com
Requires-Python: >=3.9
Requires-Dist: requests
Requires-Dist: python-dateutil
Requires-Dist: plotly>=4.0
Requires-Dist: pydantic
Requires-Dist: typing-extensions
Requires-Dist: numpy
Requires-Dist: pandas
